[{"type": "if_statement", "children": [{"type": "if", "children": []}, {"type": "boolean_operator", "children": [{"type": "boolean_operator", "children": [{"type": "not_operator", "children": [{"type": "not", "children": []}, {"type": "binary_operator", "children": [{"type": "identifier", "children": []}, {"type": "%", "children": []}, {"type": "identifier", "children": []}]}]}, {"type": "and", "children": []}, {"type": "comparison_operator", "children": [{"type": "identifier", "children": []}, {"type": ">", "children": []}, {"type": "integer", "children": []}]}]}, {"type": "and", "children": []}, {"type": "comparison_operator", "children": [{"type": "identifier", "children": []}, {"type": "in", "children": []}, {"type": "identifier", "children": []}]}]}, {"type": ":", "children": []}, {"type": "expression_statement", "children": [{"type": "call", "children": [{"type": "attribute", "children": [{"type": "identifier", "children": []}, {"type": ".", "children": []}, {"type": "identifier", "children": []}]}, {"type": "argument_list", "children": [{"type": "(", "children": []}, {"type": "identifier", "children": []}, {"type": ")", "children": []}]}]}]}]}]